Metadata-Version: 1.1
Name: alfred-genie
Version: 0.1.20200703
Summary: Genie for Alfred
Home-page: https://github.com/namuan/alfred-genie
Author: DeskRiders Dev
Author-email: me@deskriders.dev
License: MIT
Platform: any
Classifier: Development Status :: 4 - Beta
Classifier: Environment :: Console
Classifier: Intended Audience :: Developers
Classifier: License :: OSI Approved :: BSD License
Classifier: Operating System :: POSIX
Classifier: Operating System :: MacOS
Classifier: Operating System :: Unix
Classifier: Operating System :: Microsoft :: Windows
Classifier: Programming Language :: Python :: 3
Classifier: Topic :: Software Development :: Libraries :: Python Modules
